vsc/__init__.py
vsc/event_logger.py
vsc/plotly_utils.py
vsc/utils.py
vsc/mam/__init__.py
vsc/mam/account.py
vsc/mam/gbalance.py
vsc/mam/quote.py
vsc/moab/__init__.py
vsc/moab/checkjob.py
vsc/moab/checknode.py
vsc/moab/job.py
vsc/moab/showq.py
vsc/pbs/__init__.py
vsc/pbs/check.py
vsc/pbs/job.py
vsc/pbs/job_analysis.py
vsc/pbs/job_event.py
vsc/pbs/log.py
vsc/pbs/node.py
vsc/pbs/option_parser.py
vsc/pbs/pbsnodes.py
vsc/pbs/qstat.py
vsc/pbs/script_parser.py
vsc/pbs/utils.py
vsc_tools_lib_gjbex-0.9.3.dist-info/LICENSE
vsc_tools_lib_gjbex-0.9.3.dist-info/METADATA
vsc_tools_lib_gjbex-0.9.3.dist-info/WHEEL
vsc_tools_lib_gjbex-0.9.3.dist-info/top_level.txt
vsc_tools_lib_gjbex-0.9.3.dist-info/RECORD
