Metadata-Version: 2.1
Name: vsc-tools-lib-gjbex
Version: 0.9.3
Summary: Python library for interacting with PBS, Adaptive Moab and MAM
Home-page: https://github.com/gjbex/vsc-tools-lib
Author: Geert Jan Bex, Ehsan Moravveji
Author-email: geertjan.bex@uhasselt.be
License: UNKNOWN
Platform: UNKNOWN
Classifier: Programming Language :: Python :: 3
Classifier: License :: OSI Approved :: GNU General Public License v3 (GPLv3)
Classifier: Operating System :: OS Independent
License-File: LICENSE
Requires-Dist: fuzzywuzzy
Requires-Dist: validate-email
